[
    {
        "id": 555,
        "name": "Ksa Sport 1",
        "logo": "https://upload.wikimedia.org/wikipedia/ar/5/5f/%D8%B4%D8%B9%D8%A7%D8%B1_%D8%A7%D9%84%D9%82%D9%86%D9%88%D8%A7%D8%AA_%D8%A7%D9%84%D8%B1%D9%8A%D8%A7%D8%B6%D9%8A%D8%A9_%D8%A7%D9%84%D8%B3%D8%B9%D9%88%D8%AF%D9%8A%D8%A9.jpg",
        "is_hide": 0,
        "priority": 0,
        "streamsFile": "streams/555.json",
        "source_file": "19.json"
    },
    {
        "id": 556,
        "name": "KSA Sport 2",
        "logo": "https://upload.wikimedia.org/wikipedia/ar/5/5f/%D8%B4%D8%B9%D8%A7%D8%B1_%D8%A7%D9%84%D9%82%D9%86%D9%88%D8%A7%D8%AA_%D8%A7%D9%84%D8%B1%D9%8A%D8%A7%D8%B6%D9%8A%D8%A9_%D8%A7%D9%84%D8%B3%D8%B9%D9%88%D8%AF%D9%8A%D8%A9.jpg",
        "is_hide": 0,
        "priority": 0,
        "streamsFile": "streams/556.json",
        "source_file": "19.json"
    },
    {
        "id": 1574,
        "name": "KSA Sport 3",
        "logo": "https://i.imgur.com/Fa2DkKc.png",
        "is_hide": 0,
        "priority": 0,
        "streamsFile": "streams/1574.json",
        "source_file": "19.json"
    },
    {
        "id": 1812,
        "name": "KSA Sport 4",
        "logo": "https://i.imgur.com/suuVKqv.png",
        "is_hide": 0,
        "priority": 0,
        "streamsFile": "streams/1812.json",
        "source_file": "19.json"
    },
    {
        "id": 5756,
        "name": "Ksa Sport 1",
        "logo": "https://i.imgur.com/32ZwaW0.png",
        "is_hide": 0,
        "priority": 0,
        "streamsFile": "streams/5756.json",
        "source_file": "ksa_sport.json"
    },
    {
        "id": 5757,
        "name": "Ksa Sport 2",
        "logo": "https://i.imgur.com/32ZwaW0.png",
        "is_hide": 0,
        "priority": 0,
        "streamsFile": "streams/5757.json",
        "source_file": "ksa_sport.json"
    },
    {
        "id": 5758,
        "name": "Ksa Sport 3",
        "logo": "https://i.imgur.com/32ZwaW0.png",
        "is_hide": 0,
        "priority": 0,
        "streamsFile": "streams/5758.json",
        "source_file": "ksa_sport.json"
    }
]