[
  {
    "name": "1",
    "url": "https://b01c02nl.mediatriple.net/videoonlylive/mtiwaxdzdfggbnlive/broadcast_5d1b0969c3188.smil/playlist.m3u8?t=qmYu79phSpZk20PdHhtzSw&e=1779934119",
    "urlType": 3,
    "userAgent": "Mozilla/5.0 (Windows NT 10.0; Win64; x64) AppleWebKit/537.36 (KHTML, like Gecko) Chrome/139.0.0.0 Safari/537.36",
    "Referer": "https://x.com/",
    "origin": null,
    "headers": {
      "User-Agent": "Mozilla/5.0 (Windows NT 10.0; Win64; x64) AppleWebKit/537.36 (KHTML, like Gecko) Chrome/139.0.0.0 Safari/537.36",
      "Referer": "https://x.com/"
    },
    "drm": null
  },
  {
    "name": "2",
    "url": "https://panel.videoon.ly/embed/player/2/broadcast_5d1b0969c3188?autoplay=true",
    "urlType": 6,
    "userAgent": "Mozilla/5.0 (Windows NT 10.0; Win64; x64) AppleWebKit/537.36 (KHTML, like Gecko) Chrome/139.0.0.0 Safari/537.36",
    "Referer": "https://x.com/",
    "origin": null,
    "headers": {
      "User-Agent": "Mozilla/5.0 (Windows NT 10.0; Win64; x64) AppleWebKit/537.36 (KHTML, like Gecko) Chrome/139.0.0.0 Safari/537.36",
      "Referer": "https://x.com/"
    },
    "drm": null
  }
]